{
    "Message": {
        "OK Color": "Green",
        "OK Font": "Arial 24 Bold",
        "NOK Color": "Red",
        "NOK Font": "Arial 24 Bold"
    },
    "Communication Devices": {
        "_table": [
            {
                "Device Name": "Part",
                "Type": "COM",
                "COM Port": "COM5",
                "Baudrate": "115200",
                "Parity": "None",
                "Data Bits": "8",
                "Stop Bits": "1"
            },
            {
                "Device Name": "Product",
                "Type": "COM",
                "COM Port": "COM6",
                "Baudrate": "115200",
                "Parity": "None",
                "Data Bits": "8",
                "Stop Bits": "1"
            }
        ]
    },
    "Product Rules": {
        "_table": [
            {
                "Product": "0",
                "Part Voltage": "127V"
            },
            {
                "Product": "1",
                "Part Voltage": "127V"
            },
            {
                "Product": "2",
                "Part Voltage": "127V"
            },
            {
                "Product": "3",
                "Part Voltage": "127V"
            },
            {
                "Product": "A",
                "Part Voltage": "127V"
            },
            {
                "Product": "B",
                "Part Voltage": "127V"
            },
            {
                "Product": "H",
                "Part Voltage": "127V"
            },
            {
                "Product": "4",
                "Part Voltage": "240V"
            },
            {
                "Product": "5",
                "Part Voltage": "240V"
            },
            {
                "Product": "6",
                "Part Voltage": "240V"
            },
            {
                "Product": "7",
                "Part Voltage": "240V"
            },
            {
                "Product": "8",
                "Part Voltage": "240V"
            },
            {
                "Product": "9",
                "Part Voltage": "240V"
            }
        ]
    },
    "Product Matrix Mapping": {
        "Part Matrix": "55",
        "PN": "1-10",
        "Vendor": "11-18",
        "Voltage": "19-22",
        "HW Ver": "23-27",
        "FW Ver": "28-35",
        "ESP FW": "36-43",
        "Date": "44-49",
        "Serial Number": "50-55"
    },
    "SN Chassis Mapping": {
        "Product Matrix": "19",
        "Date": "1-5",
        "Type": "6-8",
        "Line": "9",
        "Serial Number": "10-13",
        "Partner": "14",
        "Voltage": "15",
        "Plug": "16",
        "Color": "17-18"
    }
}